artifactsmmo_wrapper/__init__.py
artifactsmmo_wrapper/artifacts.py
artifactsmmo_wrapper/config.py
artifactsmmo_wrapper/database.py
artifactsmmo_wrapper/exceptions.py
artifactsmmo_wrapper/game_data_classes.py
artifactsmmo_wrapper/helpers.py
artifactsmmo_wrapper/log.py
artifactsmmo_wrapper/subclasses.py
artifactsmmo_wrapper-3200.0.2.dist-info/METADATA
artifactsmmo_wrapper-3200.0.2.dist-info/WHEEL
artifactsmmo_wrapper-3200.0.2.dist-info/licenses/LICENSE
artifactsmmo_wrapper-3200.0.2.dist-info/RECORD
