Metadata-Version: 2.4
Name: artifactsmmo_wrapper
Version: 3200.0.2
Summary: A Python API Wrapper for ArtifactsMMO
Project-URL: Homepage, https://github.com/Veillax/ArtifactsMMO-Wrapper
Author-email: Veillax <contact@veillax.com>
License: GNU Affero General Public License v3
License-File: LICENSE
Classifier: License :: OSI Approved :: GNU Affero General Public License v3
Classifier: Operating System :: OS Independent
Classifier: Programming Language :: Python :: 3
Requires-Python: >=3.9
Requires-Dist: requests
